NoteMaster/__init__.py
NoteMaster/module_1.py
NoteMaster/module_2.py
NoteMaster/module_3.py
NoteMaster/module_4.py
NoteMaster/module_5.py
NoteMaster/module_6.py
NoteMaster-0.1.8.dist-info/LICENSE
NoteMaster-0.1.8.dist-info/METADATA
NoteMaster-0.1.8.dist-info/WHEEL
NoteMaster-0.1.8.dist-info/top_level.txt
NoteMaster-0.1.8.dist-info/RECORD
