Metadata-Version: 2.1
Name: NoteMaster
Version: 0.1.8
Summary: Paket untuk mengelola catatan dengan metode CRUD
Home-page: https://github.com/twelverakki/NoteMaster
Author: Kelompok 6 AP B
Author-email: twelve.rakki@gmail.com
Classifier: Programming Language :: Python :: 3
Classifier: License :: OSI Approved :: MIT License
Classifier: Operating System :: OS Independent
Requires-Python: >=3.6
License-File: LICENSE
